[
  {
    "COMPRADOR": "HENRIQUE",
    "NIVEL_SERVICO": 0,
    "MES_PENDENCIA": 0,
    "PRAZO_RUPTURA": 0,
    "PRAZO_EXCESSO": 0,
    "SKU_INDUSTRIA": 0.0,
    "PMP": 0,
    "PRAZO_CLIENTE": 0,
    "VALOR_VENDA_ATUAL": 0.0,
    "VALOR_VENDA_PROJETADA": 0.0,
    "LUCRO_PROJETO": 0.0,
    "LUCRO_REALIZADO": 0.0,
    "RUPTURA_TOTAL": 0.0,
    "EXCESSO_TOTAL": 0.0
  },
  {
    "COMPRADOR": "ALICE",
    "NIVEL_SERVICO": 0.8405643705652467,
    "MES_PENDENCIA": 2.7336354940853917,
    "PRAZO_RUPTURA": 60.0,
    "PRAZO_EXCESSO": 90.0,
    "SKU_INDUSTRIA": 1896.0,
    "PMP": 79.71734633422133,
    "PRAZO_CLIENTE": 33.0,
    "VALOR_VENDA_ATUAL": 1512658.1700000002,
    "VALOR_VENDA_PROJETADA": 3970727.7200000007,
    "LUCRO_PROJETO": 0.3113,
    "LUCRO_REALIZADO": 0.28859999999999997,
    "RUPTURA_TOTAL": 0.1285681004839507,
    "EXCESSO_TOTAL": 0.23173919599170265
  },
  {
    "COMPRADOR": "GUILHERME",
    "NIVEL_SERVICO": 0.7147258980273693,
    "MES_PENDENCIA": 3.322131139832465,
    "PRAZO_RUPTURA": 60.0,
    "PRAZO_EXCESSO": 90.0,
    "SKU_INDUSTRIA": 230.0,
    "PMP": 106.20833333333333,
    "PRAZO_CLIENTE": 0,
    "VALOR_VENDA_ATUAL": 0.0,
    "VALOR_VENDA_PROJETADA": 38050.82,
    "LUCRO_PROJETO": 0.0,
    "LUCRO_REALIZADO": 0.0,
    "RUPTURA_TOTAL": 0.1462730293601318,
    "EXCESSO_TOTAL": 0.7971024332590843
  },
  {
    "COMPRADOR": "SAMUEL",
    "NIVEL_SERVICO": 0.8570716249856337,
    "MES_PENDENCIA": 3.095094352263652,
    "PRAZO_RUPTURA": 63.333333333333336,
    "PRAZO_EXCESSO": 93.33333333333333,
    "SKU_INDUSTRIA": 2287.0,
    "PMP": 98.00448020117136,
    "PRAZO_CLIENTE": 31.814814814814813,
    "VALOR_VENDA_ATUAL": 1577056.3199999998,
    "VALOR_VENDA_PROJETADA": 4139772.86,
    "LUCRO_PROJETO": 0.27360000000000007,
    "LUCRO_REALIZADO": 0.26309999999999995,
    "RUPTURA_TOTAL": 0.08301748375765126,
    "EXCESSO_TOTAL": 0.24710943404371866
  },
  {
    "COMPRADOR": "ZILMA",
    "NIVEL_SERVICO": 0.8107861147624114,
    "MES_PENDENCIA": 2.783477351273096,
    "PRAZO_RUPTURA": 60.0,
    "PRAZO_EXCESSO": 90.0,
    "SKU_INDUSTRIA": 1125.0,
    "PMP": 93.24436507936507,
    "PRAZO_CLIENTE": 33.34782608695652,
    "VALOR_VENDA_ATUAL": 466487.44,
    "VALOR_VENDA_PROJETADA": 1224529.5500000003,
    "LUCRO_PROJETO": 0.2797,
    "LUCRO_REALIZADO": 0.27759999999999996,
    "RUPTURA_TOTAL": 0.11037219551886615,
    "EXCESSO_TOTAL": 0.24110439179599957
  },
  {
    "COMPRADOR": "DESCONTINUADO",
    "NIVEL_SERVICO": 1.0,
    "MES_PENDENCIA": 17.230239341139928,
    "PRAZO_RUPTURA": 60.0,
    "PRAZO_EXCESSO": 90.0,
    "SKU_INDUSTRIA": 0.0,
    "PMP": 0,
    "PRAZO_CLIENTE": 0,
    "VALOR_VENDA_ATUAL": 0.0,
    "VALOR_VENDA_PROJETADA": 222.03,
    "LUCRO_PROJETO": 0.0,
    "LUCRO_REALIZADO": 0.0,
    "RUPTURA_TOTAL": 0.0,
    "EXCESSO_TOTAL": 0.0
  },
  {
    "COMPRADOR": "SEM COMPRADOR",
    "NIVEL_SERVICO": 0,
    "MES_PENDENCIA": 0,
    "PRAZO_RUPTURA": 0,
    "PRAZO_EXCESSO": 0,
    "SKU_INDUSTRIA": 0,
    "PMP": 0,
    "PRAZO_CLIENTE": 0,
    "VALOR_VENDA_ATUAL": 0,
    "VALOR_VENDA_PROJETADA": 0,
    "LUCRO_PROJETO": 0,
    "LUCRO_REALIZADO": 0,
    "RUPTURA_TOTAL": 0,
    "EXCESSO_TOTAL": 0
  },
  {
    "COMPRADOR": "TOTAL",
    "NIVEL_SERVICO": 0.8353996997677922,
    "MES_PENDENCIA": 2.921777279473106,
    "PRAZO_RUPTURA": 0,
    "PRAZO_EXCESSO": 0,
    "SKU_INDUSTRIA": 5538.0,
    "PMP": 94.29363123702278,
    "PRAZO_CLIENTE": 32.720880300590444,
    "VALOR_VENDA_ATUAL": 3556201.93,
    "VALOR_VENDA_PROJETADA": 9373302.98,
    "LUCRO_PROJETO": 0.2897,
    "LUCRO_REALIZADO": 0.2746,
    "RUPTURA_TOTAL": 0.10197523087287598,
    "EXCESSO_TOTAL": 0.24594127845547456
  }
]